fluxo_aws/__init__.py
fluxo_aws/async_dynamodb_table.py
fluxo_aws/async_s3_bucket.py
fluxo_aws/auth.py
fluxo_aws/dynamodb_table.py
fluxo_aws/event_parser.py
fluxo_aws/json_encoder.py
fluxo_aws/prepare_response.py
fluxo_aws/s3_bucket.py
fluxo_aws-0.4.2.dist-info/LICENSE
fluxo_aws-0.4.2.dist-info/METADATA
fluxo_aws-0.4.2.dist-info/WHEEL
fluxo_aws-0.4.2.dist-info/top_level.txt
fluxo_aws-0.4.2.dist-info/RECORD
