Metadata-Version: 2.1
Name: fluxo-aws
Version: 0.4.2
Summary: Provides a bunch of functions and utils to help you build applications on top of Amazon Web Services Resources
Home-page: https://github.com/Fluxo-Resultados/fluxo-aws
Author: Brenno Flavio
Author-email: brenno.flavio@fluxoresultados.com.br
License: UNKNOWN
Platform: UNKNOWN
Classifier: Programming Language :: Python :: 3
Classifier: License :: OSI Approved :: MIT License
Classifier: Operating System :: OS Independent
Requires-Python: >=3.6
Requires-Dist: PyYAML (==5.3.1)
Requires-Dist: PyJWT (==1.7.1)
Requires-Dist: passlib (==1.7.2)
Requires-Dist: Cerberus (==1.3.2)
Requires-Dist: bcrypt (==3.1.7)
Requires-Dist: boto3 (==1.14.44)
Requires-Dist: aioboto3 (==8.2.0)
Requires-Dist: aiofile (==3.3.3)
